{"name":"Taiwan R User Group 資料分析上手課程影片","tagline":"","body":"今年Taiwan R User Group很高興能夠在資料科學愛好者年會上舉辦資料分析上手課程。感謝主辦單位的規劃，把整個教學過程的錄影下來，讓我們社群能夠於事後建立一個線上學習資源，讓當時沒機會參加的朋友們，可以在事後一起重新學習。\r\n這裡我們將當時使用的教材和錄影整理下來，讓想線上學習的朋友，可以在比較舒服的方式來上手R語言。請使用者們依照下面的順序一步一步的來建立R 的學習環境，以有良好的學習體驗。\r\n觀看影片時，請初學者務必不要貪快，跟著投影片和影片，一步步的重現投影片中的R 的程式碼。影片中有講師們講解程式碼的原理，投影片則方便大家可以直接複製貼上程式碼。重現範例程式碼，以及理解運作的原理，就是學習一個程式語言最好的方法。\r\n\r\n## 取得幫助的方法\r\n\r\n由於我們沒有人力建立長期回應問題的平台，所以歡迎所有在操作以下手續的使用者，以及在學習中遇到任何問題的使用者，請到 <https://github.com/TaiwanRUserGroup/DSC2014Tutorial/issues> 發問（需要註冊github帳號）。於R以及其套件更新快速，所以很您可能現在的操作過程會發生問題，這很可能不是您的錯，但是我們也沒有人力長期檢測以下的步驟是否可以順利完成。請大家抱持的幫助未來的使用者的心態，不吝於在上述連結中向我們報告錯誤。您的回報可以讓未來其他使用者更方便的，也是對這個開放教材很大的貢獻。\r\n另外以下也列出當你遇到其他R 的問題時，可以找到幫助的頻道：\r\n\r\n- ptt R_Language版\r\n- 中華R軟體學會的討論區 https://groups.google.com/forum/#!forum/taiwanruser\r\n- 週一晚上至政大公企中心舉辦的 MLDM Monday 找我們的 Officer 求救。(活動資訊: http://www.meetup.com/Taiwan-R)\r\n- Taiwan R User Group 的 mailing list。請在加入 meetup 中的社群之後寫信至 Taiwan-useR-Group-list@meetup.com\r\n\r\n## 建立學習環境\r\n\r\n初學使用者請依照以下列出的文件，安裝 R 3.1.2 版本或更新的版本。\r\n\r\n### 安裝R 3.1以上版本\r\n\r\n#### Windows\r\n\r\n請至 [CRAN](http://cran.csie.ntu.edu.tw) 上下載 R3.1 以上的安裝程式。\r\n\r\n或參考 [![在Windows上安裝R](http://img.youtube.com/vi/FsOHPGUIDZU/0.jpg)](http://www.youtube.com/watch?v=FsOHPGUIDZU)\r\n\r\n","google":"","note":"Don't delete this file! It's used internally to help with page regeneration."}